colorss/__init__.py
colorss/colorss.py
colorss-0.1.0.dist-info/licenses/LICENSE
colourama/__init__.py
colourama/colorss.py
colourama/colourama.py
colorss-0.1.0.dist-info/METADATA
colorss-0.1.0.dist-info/WHEEL
colorss-0.1.0.dist-info/top_level.txt
colorss-0.1.0.dist-info/RECORD
