Metadata-Version: 2.4
Name: colorss
Version: 0.1.0
Summary: colors's
Author: Paradox
Classifier: Programming Language :: Python :: 3
Classifier: License :: OSI Approved :: MIT License
Classifier: Operating System :: OS Independent
Requires-Python: >=3.6
License-File: LICENSE
Dynamic: author
Dynamic: classifier
Dynamic: license-file
Dynamic: requires-python
Dynamic: summary
